idoc/__init__.py
idoc/configuration.py
idoc/debug.py
idoc/decorators.py
idoc/exceptions.py
idoc/helpers.py
idoc/orevent.py
idoc/postinstall.py
idoc/client/__init__.py
idoc/client/analysis/__init__.py
idoc/client/analysis/analysis.py
idoc/client/bin/__init__.py
idoc/client/bin/cli.py
idoc/client/bin/client.py
idoc/client/utils/__init__.py
idoc/client/utils/device_scanner.py
idoc/client/utils/logging_server.py
idoc/client/utils/mixins.py
idoc/scripts/__init__.py
idoc/scripts/generate_config.py
idoc/scripts/generate_logging_config.py
idoc/server/__init__.py
idoc/server/bin/__init__.py
idoc/server/bin/control.py
idoc/server/bin/offline.py
idoc/server/bin/parser.py
idoc/server/bin/server.py
idoc/server/controllers/__init__.py
idoc/server/controllers/boards.py
idoc/server/controllers/controllers.py
idoc/server/controllers/threads.py
idoc/server/core/__init__.py
idoc/server/core/base.py
idoc/server/core/control_thread.py
idoc/server/core/data_point.py
idoc/server/core/recognizer.py
idoc/server/core/roi.py
idoc/server/core/tracking_unit.py
idoc/server/core/variables.py
idoc/server/drawers/__init__.py
idoc/server/drawers/drawers.py
idoc/server/hardware/__init__.py
idoc/server/hardware/interfaces/__init__.py
idoc/server/hardware/interfaces/interfaces.py
idoc/server/io/__init__.py
idoc/server/io/cameras.py
idoc/server/io/opencv_camera.py
idoc/server/io/pylon_camera.py
idoc/server/io/result_writer.py
idoc/server/programmers/__init__.py
idoc/server/programmers/programmers.py
idoc/server/roi_builders/__init__.py
idoc/server/roi_builders/helpers.py
idoc/server/roi_builders/high_contrast_roi_builder.py
idoc/server/roi_builders/roi_builders.py
idoc/server/roi_builders/target_roi_builder.py
idoc/server/stimulators/__init__.py
idoc/server/stimulators/odour_stimulators.py
idoc/server/stimulators/optomotor_stimulators.py
idoc/server/stimulators/sleep_depriver_stimulators.py
idoc/server/stimulators/stimulators.py
idoc/server/trackers/__init__.py
idoc-2.1.8.dist-info/LICENSE
idoc-2.1.8.dist-info/METADATA
idoc-2.1.8.dist-info/WHEEL
idoc-2.1.8.dist-info/dependency_links.txt
idoc-2.1.8.dist-info/entry_points.txt
idoc-2.1.8.dist-info/top_level.txt
idoc-2.1.8.dist-info/RECORD
