Metadata-Version: 2.1
Name: idoc
Version: 2.1.8
Summary: Individual Drosophila Optogenetics Conditioner
Home-page: https://github.com/shaliulab/idoc
Author: Antonio Ortega
Author-email: antonio.ortega@kuleuven.be
Classifier: Programming Language :: Python :: 3
Classifier: License :: OSI Approved :: GNU General Public License v3 (GPLv3)
Requires-Python: >=3.8.10
License-File: LICENSE
Requires-Dist: pypylon
Requires-Dist: opencv-python >=4.1.1
Requires-Dist: pyserial >=3.4
Requires-Dist: scipy
Requires-Dist: numpy
Requires-Dist: pandas
Requires-Dist: pyfirmata
Requires-Dist: pyaml
Requires-Dist: coloredlogs
Requires-Dist: bottle
Requires-Dist: cheroot
Requires-Dist: netifaces
Requires-Dist: requests
